flagsup/__init__.py
flagsup/cached_client.py
flagsup/client.py
flagsup/client_sdk.py
flagsup/constants.py
flagsup/utils.py
flagsup-0.0.2.dist-info/METADATA
flagsup-0.0.2.dist-info/WHEEL
flagsup-0.0.2.dist-info/top_level.txt
flagsup-0.0.2.dist-info/RECORD
