Metadata-Version: 2.1
Name: flagsup
Version: 0.0.2
Summary: A Feature Flags management SDK
Home-page: UNKNOWN
Author: Tri Tran
Author-email: tri.tm@teko.vn
License: UNKNOWN
Platform: UNKNOWN
